{
  "object" : {
    "artifacts" : [
      {
        "packageRef" : {
          "identity" : "events-kmp",
          "kind" : "root",
          "location" : "/Users/victoriaaloy/Projects/events-kmp",
          "name" : "events-kmp"
        },
        "path" : "/Users/victoriaaloy/Projects/events-kmp/.build/artifacts/events-kmp/shared.xcframework",
        "source" : {
          "checksum" : "cca8fc079140d04f9398acec28a881e3b0c5257bb76dee01f0bafc8f6257e056",
          "type" : "local"
        },
        "targetName" : "shared"
      }
    ],
    "dependencies" : [

    ]
  },
  "version" : 5
}